{
    "version": "1.0.0",
    "routes": [
        {
            "path": "*/admin/attendance/settings",
            "layout": "admin_attendance_settings",
            "auth_required": true,
            "meta": {
                "title": "$t:lastorder-attendance.admin.settings.title",
                "permission": "lastorder-attendance.settings.read"
            }
        },
        {
            "path": "*/admin/attendance",
            "layout": "admin_attendance_index",
            "auth_required": true,
            "meta": {
                "title": "$t:lastorder-attendance.admin.attendance.title",
                "permission": "lastorder-attendance.attendance.read"
            }
        }
    ]
}
